confluence_rag_indexer/__init__.py
confluence_rag_indexer/confluence.py
confluence_rag_indexer/indexer.py
confluence_rag_indexer-0.2.0.dist-info/METADATA
confluence_rag_indexer-0.2.0.dist-info/WHEEL
confluence_rag_indexer-0.2.0.dist-info/entry_points.txt
confluence_rag_indexer-0.2.0.dist-info/licenses/LICENSE
confluence_rag_indexer-0.2.0.dist-info/RECORD
