Metadata-Version: 2.4
Name: confluence-rag-indexer
Version: 0.2.0
Summary: A tool to index Confluence content for RAG
Project-URL: Repository, https://github.com/gmr/confluence-rag-indexer.git
Author-email: "Gavin M. Roy" <gavinmroy@gmail.com>
License: BSD 3-Clause License
License-File: LICENSE
Classifier: Development Status :: 3 - Alpha
Classifier: Intended Audience :: Developers
Classifier: License :: OSI Approved :: BSD License
Classifier: Natural Language :: English
Classifier: Programming Language :: Python :: 3.12
Classifier: Programming Language :: Python :: 3.13
Classifier: Topic :: Database
Classifier: Topic :: Scientific/Engineering :: Artificial Intelligence
Requires-Python: >=3.12
Requires-Dist: httpx
Requires-Dist: markdownify
Requires-Dist: pgvector-rag>=0.4.0
Provides-Extra: dev
Requires-Dist: build; extra == 'dev'
Requires-Dist: coverage; extra == 'dev'
Requires-Dist: ruff; extra == 'dev'
